mechafil/__init__.py
mechafil/data.py
mechafil/data_spacescope.py
mechafil/data_starboard.py
mechafil/locking.py
mechafil/minting.py
mechafil/power.py
mechafil/sim.py
mechafil/supply.py
mechafil/utils.py
mechafil/vesting.py
mechaFIL-1.9.dist-info/LICENSE
mechaFIL-1.9.dist-info/METADATA
mechaFIL-1.9.dist-info/WHEEL
mechaFIL-1.9.dist-info/top_level.txt
mechaFIL-1.9.dist-info/RECORD
