Metadata-Version: 2.1
Name: mechaFIL
Version: 1.9
Summary: Mechanistic model for the Filecoin Economy
Author: Maria Silva, Tom Mellan, Kiran Karra
Author-email: misilva73@gmail.com, t.mellan@imperial.ac.uk, kiran.karra@gmail.com
Project-URL: Documentation, https://github.com/protocol/filecoin-mecha-twin
Project-URL: Source, https://github.com/protocol/filecoin-mecha-twin
Classifier: Programming Language :: Python :: 3
Classifier: License :: OSI Approved :: MIT License
Classifier: Operating System :: OS Independent
Requires-Python: >=3.8
License-File: LICENSE
Requires-Dist: numpy (>=1.22)
Requires-Dist: pandas (>=1.4)
Requires-Dist: requests (>=2.28)
